growtopia/__init__.py
growtopia/client.py
growtopia/collection.py
growtopia/constants.py
growtopia/context.py
growtopia/dialog.py
growtopia/dispatcher.py
growtopia/enums.py
growtopia/error_manager.py
growtopia/exceptions.py
growtopia/file.py
growtopia/host.py
growtopia/item.py
growtopia/items_data.py
growtopia/listener.py
growtopia/player_tribute.py
growtopia/server.py
growtopia/player/__init__.py
growtopia/player/player.py
growtopia/player/player_login_info.py
growtopia/player/player_net.py
growtopia/protocol/__init__.py
growtopia/protocol/enums.py
growtopia/protocol/game_message_packet.py
growtopia/protocol/game_update_packet.py
growtopia/protocol/hello_packet.py
growtopia/protocol/packet.py
growtopia/protocol/text_packet.py
growtopia/protocol/variant.py
growtopia/protocol/variant_list.py
growtopia.py-0.1.2.dist-info/LICENSE
growtopia.py-0.1.2.dist-info/METADATA
growtopia.py-0.1.2.dist-info/WHEEL
growtopia.py-0.1.2.dist-info/top_level.txt
growtopia.py-0.1.2.dist-info/RECORD
