Metadata-Version: 2.1
Name: growtopia.py
Version: 0.1.2
Summary: A simple asynchronous API for Growtopia, capable of creating servers, clients, and more!
License: MIT License
Project-URL: Homepage, https://github.com/kaJob-dev/growtopia.py
Project-URL: Bug Tracker, https://github.com/kaJob-dev/growtopia.py/issues
Classifier: Programming Language :: Python :: 3.11
Classifier: Programming Language :: Python :: 3.10
Classifier: Programming Language :: Python :: 3.9
Classifier: License :: OSI Approved :: MIT License
Classifier: Operating System :: OS Independent
Requires-Python: >=3.9.0
License-File: LICENSE
Requires-Dist: aiofiles
